odoo/addons/herd/README.rst
odoo/addons/herd/__init__.py
odoo/addons/herd/__manifest__.py
odoo/addons/herd/data/animal_species.xml
odoo/addons/herd/i18n/fr.po
odoo/addons/herd/i18n/herd.pot
odoo/addons/herd/models/__init__.py
odoo/addons/herd/models/animal.py
odoo/addons/herd/models/herd.py
odoo/addons/herd/models/specie.py
odoo/addons/herd/readme/CONTIBUTORS.rst
odoo/addons/herd/readme/DESCRIPTION.rst
odoo/addons/herd/security/ir.model.access.csv
odoo/addons/herd/static/description/bois-joli.png
odoo/addons/herd/static/description/icon.png
odoo/addons/herd/static/description/index.html
odoo/addons/herd/static/description/marguerite.png
odoo/addons/herd/views/animal.xml
odoo/addons/herd/views/herd.xml
odoo/addons/herd/views/specie.xml
odoo14_addon_herd-14.0.1.1.0.dist-info/METADATA
odoo14_addon_herd-14.0.1.1.0.dist-info/WHEEL
odoo14_addon_herd-14.0.1.1.0.dist-info/top_level.txt
odoo14_addon_herd-14.0.1.1.0.dist-info/RECORD
